[{"svg":"gchq.svg","board":"gchq.board","creditText":"GCHQ","creditUrl":"http://www.gchq.gov.uk/press_and_media/news_and_features/Pages/Directors-Christmas-puzzle-2015.aspx","name":"GCHQ's Christmas Puzzle"},{"svg":"alien.sgriddler.svg","board":"alien.sgriddler.board","creditText":"jsimlo.sk","creditUrl":"http://jsimlo.sk/griddlers","name":"alien"},{"svg":"anime.sgriddler.svg","board":"anime.sgriddler.board","creditText":"jsimlo.sk","creditUrl":"http://jsimlo.sk/griddlers","name":"anime"},{"svg":"appaloosa.sgriddler.svg","board":"appaloosa.sgriddler.board","creditText":"jsimlo.sk","creditUrl":"http://jsimlo.sk/griddlers","name":"appaloosa"},{"svg":"aquarius.sgriddler.svg","board":"aquarius.sgriddler.board","creditText":"jsimlo.sk","creditUrl":"http://jsimlo.sk/griddlers","name":"aquarius"},{"svg":"badger.sgriddler.svg","board":"badger.sgriddler.board","creditText":"jsimlo.sk","creditUrl":"http://jsimlo.sk/griddlers","name":"badger"},{"svg":"bear1.sgriddler.svg","board":"bear1.sgriddler.board","creditText":"jsimlo.sk","creditUrl":"http://jsimlo.sk/griddlers","name":"bear1"},{"svg":"bear2.sgriddler.svg","board":"bear2.sgriddler.board","creditText":"jsimlo.sk","creditUrl":"http://jsimlo.sk/griddlers","name":"bear2"},{"svg":"bird.sgriddler.svg","board":"bird.sgriddler.board","creditText":"jsimlo.sk","creditUrl":"http://jsimlo.sk/griddlers","name":"bird"},{"svg":"blackbird.sgriddler.svg","board":"blackbird.sgriddler.board","creditText":"jsimlo.sk","creditUrl":"http://jsimlo.sk/griddlers","name":"blackbird"},{"svg":"bull.sgriddler.svg","board":"bull.sgriddler.board","creditText":"jsimlo.sk","creditUrl":"http://jsimlo.sk/griddlers","name":"bull"},{"svg":"butterfly.sgriddler.svg","board":"butterfly.sgriddler.board","creditText":"jsimlo.sk","creditUrl":"http://jsimlo.sk/griddlers","name":"butterfly"},{"svg":"calimero.sgriddler.svg","board":"calimero.sgriddler.board","creditText":"jsimlo.sk","creditUrl":"http://jsimlo.sk/griddlers","name":"calimero"},{"svg":"campfire.sgriddler.svg","board":"campfire.sgriddler.board","creditText":"jsimlo.sk","creditUrl":"http://jsimlo.sk/griddlers","name":"campfire"},{"svg":"car.sgriddler.svg","board":"car.sgriddler.board","creditText":"jsimlo.sk","creditUrl":"http://jsimlo.sk/griddlers","name":"car"},{"svg":"checkmate.sgriddler.svg","board":"checkmate.sgriddler.board","creditText":"jsimlo.sk","creditUrl":"http://jsimlo.sk/griddlers","name":"checkmate"},{"svg":"cobra.sgriddler.svg","board":"cobra.sgriddler.board","creditText":"jsimlo.sk","creditUrl":"http://jsimlo.sk/griddlers","name":"cobra"},{"svg":"cottage1.sgriddler.svg","board":"cottage1.sgriddler.board","creditText":"jsimlo.sk","creditUrl":"http://jsimlo.sk/griddlers","name":"cottage1"},{"svg":"cottage2.sgriddler.svg","board":"cottage2.sgriddler.board","creditText":"jsimlo.sk","creditUrl":"http://jsimlo.sk/griddlers","name":"cottage2"},{"svg":"cow.sgriddler.svg","board":"cow.sgriddler.board","creditText":"jsimlo.sk","creditUrl":"http://jsimlo.sk/griddlers","name":"cow"},{"svg":"cube.sgriddler.svg","board":"cube.sgriddler.board","creditText":"jsimlo.sk","creditUrl":"http://jsimlo.sk/griddlers","name":"cube"},{"svg":"dance.sgriddler.svg","board":"dance.sgriddler.board","creditText":"jsimlo.sk","creditUrl":"http://jsimlo.sk/griddlers","name":"dance"},{"svg":"dante.sgriddler.svg","board":"dante.sgriddler.board","creditText":"jsimlo.sk","creditUrl":"http://jsimlo.sk/griddlers","name":"dante"},{"svg":"dog.sgriddler.svg","board":"dog.sgriddler.board","creditText":"jsimlo.sk","creditUrl":"http://jsimlo.sk/griddlers","name":"dog"},{"svg":"doggie.sgriddler.svg","board":"doggie.sgriddler.board","creditText":"jsimlo.sk","creditUrl":"http://jsimlo.sk/griddlers","name":"doggie"},{"svg":"donkey.sgriddler.svg","board":"donkey.sgriddler.board","creditText":"jsimlo.sk","creditUrl":"http://jsimlo.sk/griddlers","name":"donkey"},{"svg":"dragon.sgriddler.svg","board":"dragon.sgriddler.board","creditText":"jsimlo.sk","creditUrl":"http://jsimlo.sk/griddlers","name":"dragon"},{"svg":"dragon2.sgriddler.svg","board":"dragon2.sgriddler.board","creditText":"jsimlo.sk","creditUrl":"http://jsimlo.sk/griddlers","name":"dragon2"},{"svg":"drakkar.sgriddler.svg","board":"drakkar.sgriddler.board","creditText":"jsimlo.sk","creditUrl":"http://jsimlo.sk/griddlers","name":"drakkar"},{"svg":"eagle.sgriddler.svg","board":"eagle.sgriddler.board","creditText":"jsimlo.sk","creditUrl":"http://jsimlo.sk/griddlers","name":"eagle"},{"svg":"ernie.sgriddler.svg","board":"ernie.sgriddler.board","creditText":"jsimlo.sk","creditUrl":"http://jsimlo.sk/griddlers","name":"ernie"},{"svg":"face.sgriddler.svg","board":"face.sgriddler.board","creditText":"jsimlo.sk","creditUrl":"http://jsimlo.sk/griddlers","name":"face"},{"svg":"feeding.sgriddler.svg","board":"feeding.sgriddler.board","creditText":"jsimlo.sk","creditUrl":"http://jsimlo.sk/griddlers","name":"feeding"},{"svg":"fish.sgriddler.svg","board":"fish.sgriddler.board","creditText":"jsimlo.sk","creditUrl":"http://jsimlo.sk/griddlers","name":"fish"},{"svg":"flower.sgriddler.svg","board":"flower.sgriddler.board","creditText":"jsimlo.sk","creditUrl":"http://jsimlo.sk/griddlers","name":"flower"},{"svg":"football.sgriddler.svg","board":"football.sgriddler.board","creditText":"jsimlo.sk","creditUrl":"http://jsimlo.sk/griddlers","name":"football"},{"svg":"frog.sgriddler.svg","board":"frog.sgriddler.board","creditText":"jsimlo.sk","creditUrl":"http://jsimlo.sk/griddlers","name":"frog"},{"svg":"fruits.sgriddler.svg","board":"fruits.sgriddler.board","creditText":"jsimlo.sk","creditUrl":"http://jsimlo.sk/griddlers","name":"fruits"},{"svg":"galleon1.sgriddler.svg","board":"galleon1.sgriddler.board","creditText":"jsimlo.sk","creditUrl":"http://jsimlo.sk/griddlers","name":"galleon1"},{"svg":"galleon3.sgriddler.svg","board":"galleon3.sgriddler.board","creditText":"jsimlo.sk","creditUrl":"http://jsimlo.sk/griddlers","name":"galleon3"},{"svg":"galleon4.sgriddler.svg","board":"galleon4.sgriddler.board","creditText":"jsimlo.sk","creditUrl":"http://jsimlo.sk/griddlers","name":"galleon4"},{"svg":"genie.sgriddler.svg","board":"genie.sgriddler.board","creditText":"jsimlo.sk","creditUrl":"http://jsimlo.sk/griddlers","name":"genie"},{"svg":"giraffe.sgriddler.svg","board":"giraffe.sgriddler.board","creditText":"jsimlo.sk","creditUrl":"http://jsimlo.sk/griddlers","name":"giraffe"},{"svg":"grapes.sgriddler.svg","board":"grapes.sgriddler.board","creditText":"jsimlo.sk","creditUrl":"http://jsimlo.sk/griddlers","name":"grapes"},{"svg":"heavymetal.sgriddler.svg","board":"heavymetal.sgriddler.board","creditText":"jsimlo.sk","creditUrl":"http://jsimlo.sk/griddlers","name":"heavymetal"},{"svg":"hedgehog.sgriddler.svg","board":"hedgehog.sgriddler.board","creditText":"jsimlo.sk","creditUrl":"http://jsimlo.sk/griddlers","name":"hedgehog"},{"svg":"herrculestower.sgriddler.svg","board":"herrculestower.sgriddler.board","creditText":"jsimlo.sk","creditUrl":"http://jsimlo.sk/griddlers","name":"herrculestower"},{"svg":"horse1.sgriddler.svg","board":"horse1.sgriddler.board","creditText":"jsimlo.sk","creditUrl":"http://jsimlo.sk/griddlers","name":"horse1"},{"svg":"horse2.sgriddler.svg","board":"horse2.sgriddler.board","creditText":"jsimlo.sk","creditUrl":"http://jsimlo.sk/griddlers","name":"horse2"},{"svg":"horse3.sgriddler.svg","board":"horse3.sgriddler.board","creditText":"jsimlo.sk","creditUrl":"http://jsimlo.sk/griddlers","name":"horse3"},{"svg":"horse4.sgriddler.svg","board":"horse4.sgriddler.board","creditText":"jsimlo.sk","creditUrl":"http://jsimlo.sk/griddlers","name":"horse4"},{"svg":"house.sgriddler.svg","board":"house.sgriddler.board","creditText":"jsimlo.sk","creditUrl":"http://jsimlo.sk/griddlers","name":"house"},{"svg":"hurdler.sgriddler.svg","board":"hurdler.sgriddler.board","creditText":"jsimlo.sk","creditUrl":"http://jsimlo.sk/griddlers","name":"hurdler"},{"svg":"huskie.sgriddler.svg","board":"huskie.sgriddler.board","creditText":"jsimlo.sk","creditUrl":"http://jsimlo.sk/griddlers","name":"huskie"},{"svg":"jaguar.sgriddler.svg","board":"jaguar.sgriddler.board","creditText":"jsimlo.sk","creditUrl":"http://jsimlo.sk/griddlers","name":"jaguar"},{"svg":"jester.sgriddler.svg","board":"jester.sgriddler.board","creditText":"jsimlo.sk","creditUrl":"http://jsimlo.sk/griddlers","name":"jester"},{"svg":"kart.sgriddler.svg","board":"kart.sgriddler.board","creditText":"jsimlo.sk","creditUrl":"http://jsimlo.sk/griddlers","name":"kart"},{"svg":"katherine.sgriddler.svg","board":"katherine.sgriddler.board","creditText":"jsimlo.sk","creditUrl":"http://jsimlo.sk/griddlers","name":"katherine"},{"svg":"kittie.sgriddler.svg","board":"kittie.sgriddler.board","creditText":"jsimlo.sk","creditUrl":"http://jsimlo.sk/griddlers","name":"kittie"},{"svg":"lady.sgriddler.svg","board":"lady.sgriddler.board","creditText":"jsimlo.sk","creditUrl":"http://jsimlo.sk/griddlers","name":"lady"},{"svg":"man1.sgriddler.svg","board":"man1.sgriddler.board","creditText":"jsimlo.sk","creditUrl":"http://jsimlo.sk/griddlers","name":"man1"},{"svg":"man2.sgriddler.svg","board":"man2.sgriddler.board","creditText":"jsimlo.sk","creditUrl":"http://jsimlo.sk/griddlers","name":"man2"},{"svg":"mississippi.sgriddler.svg","board":"mississippi.sgriddler.board","creditText":"jsimlo.sk","creditUrl":"http://jsimlo.sk/griddlers","name":"mississippi"},{"svg":"monkey.sgriddler.svg","board":"monkey.sgriddler.board","creditText":"jsimlo.sk","creditUrl":"http://jsimlo.sk/griddlers","name":"monkey"},{"svg":"moon1.sgriddler.svg","board":"moon1.sgriddler.board","creditText":"jsimlo.sk","creditUrl":"http://jsimlo.sk/griddlers","name":"moon1"},{"svg":"moon2.sgriddler.svg","board":"moon2.sgriddler.board","creditText":"jsimlo.sk","creditUrl":"http://jsimlo.sk/griddlers","name":"moon2"},{"svg":"music.sgriddler.svg","board":"music.sgriddler.board","creditText":"jsimlo.sk","creditUrl":"http://jsimlo.sk/griddlers","name":"music"},{"svg":"mustang.sgriddler.svg","board":"mustang.sgriddler.board","creditText":"jsimlo.sk","creditUrl":"http://jsimlo.sk/griddlers","name":"mustang"},{"svg":"nicole.sgriddler.svg","board":"nicole.sgriddler.board","creditText":"jsimlo.sk","creditUrl":"http://jsimlo.sk/griddlers","name":"nicole"},{"svg":"nipper.sgriddler.svg","board":"nipper.sgriddler.board","creditText":"jsimlo.sk","creditUrl":"http://jsimlo.sk/griddlers","name":"nipper"},{"svg":"ogle.sgriddler.svg","board":"ogle.sgriddler.board","creditText":"jsimlo.sk","creditUrl":"http://jsimlo.sk/griddlers","name":"ogle"},{"svg":"oldlace.sgriddler.svg","board":"oldlace.sgriddler.board","creditText":"jsimlo.sk","creditUrl":"http://jsimlo.sk/griddlers","name":"oldlace"},{"svg":"oldman.sgriddler.svg","board":"oldman.sgriddler.board","creditText":"jsimlo.sk","creditUrl":"http://jsimlo.sk/griddlers","name":"oldman"},{"svg":"owl.sgriddler.svg","board":"owl.sgriddler.board","creditText":"jsimlo.sk","creditUrl":"http://jsimlo.sk/griddlers","name":"owl"},{"svg":"pacifier.sgriddler.svg","board":"pacifier.sgriddler.board","creditText":"jsimlo.sk","creditUrl":"http://jsimlo.sk/griddlers","name":"pacifier"},{"svg":"pagoda.sgriddler.svg","board":"pagoda.sgriddler.board","creditText":"jsimlo.sk","creditUrl":"http://jsimlo.sk/griddlers","name":"pagoda"},{"svg":"parade.sgriddler.svg","board":"parade.sgriddler.board","creditText":"jsimlo.sk","creditUrl":"http://jsimlo.sk/griddlers","name":"parade"},{"svg":"picnic.sgriddler.svg","board":"picnic.sgriddler.board","creditText":"jsimlo.sk","creditUrl":"http://jsimlo.sk/griddlers","name":"picnic"},{"svg":"pony.sgriddler.svg","board":"pony.sgriddler.board","creditText":"jsimlo.sk","creditUrl":"http://jsimlo.sk/griddlers","name":"pony"},{"svg":"puppy2.sgriddler.svg","board":"puppy2.sgriddler.board","creditText":"jsimlo.sk","creditUrl":"http://jsimlo.sk/griddlers","name":"puppy2"},{"svg":"rose1.sgriddler.svg","board":"rose1.sgriddler.board","creditText":"jsimlo.sk","creditUrl":"http://jsimlo.sk/griddlers","name":"rose1"},{"svg":"rose3.sgriddler.svg","board":"rose3.sgriddler.board","creditText":"jsimlo.sk","creditUrl":"http://jsimlo.sk/griddlers","name":"rose3"},{"svg":"sail.sgriddler.svg","board":"sail.sgriddler.board","creditText":"jsimlo.sk","creditUrl":"http://jsimlo.sk/griddlers","name":"sail"},{"svg":"santa.sgriddler.svg","board":"santa.sgriddler.board","creditText":"jsimlo.sk","creditUrl":"http://jsimlo.sk/griddlers","name":"santa"},{"svg":"saracen.sgriddler.svg","board":"saracen.sgriddler.board","creditText":"jsimlo.sk","creditUrl":"http://jsimlo.sk/griddlers","name":"saracen"},{"svg":"scale.sgriddler.svg","board":"scale.sgriddler.board","creditText":"jsimlo.sk","creditUrl":"http://jsimlo.sk/griddlers","name":"scale"},{"svg":"shark.sgriddler.svg","board":"shark.sgriddler.board","creditText":"jsimlo.sk","creditUrl":"http://jsimlo.sk/griddlers","name":"shark"},{"svg":"smurf.sgriddler.svg","board":"smurf.sgriddler.board","creditText":"jsimlo.sk","creditUrl":"http://jsimlo.sk/griddlers","name":"smurf"},{"svg":"snowboarder.sgriddler.svg","board":"snowboarder.sgriddler.board","creditText":"jsimlo.sk","creditUrl":"http://jsimlo.sk/griddlers","name":"snowboarder"},{"svg":"superman.sgriddler.svg","board":"superman.sgriddler.board","creditText":"jsimlo.sk","creditUrl":"http://jsimlo.sk/griddlers","name":"superman"},{"svg":"teddybear.sgriddler.svg","board":"teddybear.sgriddler.board","creditText":"jsimlo.sk","creditUrl":"http://jsimlo.sk/griddlers","name":"teddybear"},{"svg":"truck.sgriddler.svg","board":"truck.sgriddler.board","creditText":"jsimlo.sk","creditUrl":"http://jsimlo.sk/griddlers","name":"truck"},{"svg":"vikingsboat.sgriddler.svg","board":"vikingsboat.sgriddler.board","creditText":"jsimlo.sk","creditUrl":"http://jsimlo.sk/griddlers","name":"vikingsboat"},{"svg":"waltz.sgriddler.svg","board":"waltz.sgriddler.board","creditText":"jsimlo.sk","creditUrl":"http://jsimlo.sk/griddlers","name":"waltz"},{"svg":"witch.sgriddler.svg","board":"witch.sgriddler.board","creditText":"jsimlo.sk","creditUrl":"http://jsimlo.sk/griddlers","name":"witch"},{"svg":"wolf.sgriddler.svg","board":"wolf.sgriddler.board","creditText":"jsimlo.sk","creditUrl":"http://jsimlo.sk/griddlers","name":"wolf"},{"svg":"woman1.sgriddler.svg","board":"woman1.sgriddler.board","creditText":"jsimlo.sk","creditUrl":"http://jsimlo.sk/griddlers","name":"woman1"},{"svg":"woman2.sgriddler.svg","board":"woman2.sgriddler.board","creditText":"jsimlo.sk","creditUrl":"http://jsimlo.sk/griddlers","name":"woman2"},{"svg":"worker.sgriddler.svg","board":"worker.sgriddler.board","creditText":"jsimlo.sk","creditUrl":"http://jsimlo.sk/griddlers","name":"worker"},{"svg":"zoo.sgriddler.svg","board":"zoo.sgriddler.board","creditText":"jsimlo.sk","creditUrl":"http://jsimlo.sk/griddlers","name":"zoo"}]
